rithmetic/Base.py
rithmetic/__init__.py
rithmetic/func.py
rithmetic/rith.py
rithmetic-0.0.19.dist-info/licenses/LICENSE.md
rithmetic-0.0.19.dist-info/METADATA
rithmetic-0.0.19.dist-info/WHEEL
rithmetic-0.0.19.dist-info/entry_points.txt
rithmetic-0.0.19.dist-info/top_level.txt
rithmetic-0.0.19.dist-info/RECORD
