Metadata-Version: 2.4
Name: rithmetic
Version: 0.0.19
Summary: Simple arithmetic lib for students
Home-page: https://github.com/Prashant-Aswal/rithmetic
Author: PrashantAswal
Author-email: prashant.aswal89@gmail.com
License: MIT
Classifier: License :: OSI Approved :: MIT License
Classifier: Programming Language :: Python :: 3.12
Classifier: Operating System :: OS Independent
License-File: LICENSE.md
Dynamic: author
Dynamic: author-email
Dynamic: classifier
Dynamic: description
Dynamic: description-content-type
Dynamic: home-page
Dynamic: license
Dynamic: license-file
Dynamic: summary
